{
  "headers": {
    "x-amz-request-id": "B21ECC17DD235227",
    "last-modified": "Sat, 31 Oct 2020 14:34:08 GMT",
    "date": "Fri, 06 Nov 2020 18:40:19 GMT",
    "x-amz-version-id": "IW_sg_umMm2dNFOSipTfC7qqxqeCXcuH",
    "report-to": "{\"endpoints\":[{\"url\":\"https:\\/\\/a.nel.cloudflare.com\\/report?s=IS3ykocCxt0UC3m8s%2BXW56QpIKHOgG71wJf5ZxZGbb7r0aryxjEYt8T3kDEWhk6LpBYTppP3TZfP2IImf89LLL1C0Uw8Fuq%2B8Uk%3D\"}],\"group\":\"cf-nel\",\"max_age\":604800}",
    "cf-request-id": "06407517d90000ceb8643e0000000001",
    "vary": "Accept-Encoding",
    "etag": "\"6870044aa372f58566b6cb31d954fe66\"",
    "cf-cache-status": "HIT",
    "content-type": "application/typescript; charset=utf-8",
    "content-length": "5465",
    "accept-ranges": "bytes",
    "nel": "{\"report_to\":\"cf-nel\",\"max_age\":604800}",
    "age": "533171",
    "expect-ct": "max-age=604800, report-uri=\"https://report-uri.cloudflare.com/cdn-cgi/beacon/expect-ct\"",
    "cache-control": "public, max-age=31536000, immutable",
    "access-control-allow-origin": "*",
    "server": "cloudflare",
    "set-cookie": "__cfduid=d61e7b6af7ccda5647172af9c2ba190d31604688019; expires=Sun, 06-Dec-20 18:40:19 GMT; path=/; domain=.deno.land; HttpOnly; SameSite=Lax; Secure",
    "x-amz-id-2": "g866BU8B/zc05TBYyscHsMN/RMx0sOOPjTFtLFzKJPoeFvkVfXT+B5XsxU/LYPZcui4vV8tWed4=",
    "cf-ray": "5ee0f13959deceb8-IAD"
  },
  "url": "https://deno.land/std@0.76.0/testing/_diff.ts"
}