{
  "headers": {
    "nel": "{\"report_to\":\"cf-nel\",\"max_age\":604800}",
    "set-cookie": "__cfduid=db0dd13647b95aa7aa45966157c59cbff1604788349; expires=Mon, 07-Dec-20 22:32:29 GMT; path=/; domain=.deno.land; HttpOnly; SameSite=Lax; Secure",
    "cf-ray": "5eea82b158c17415-IAD",
    "last-modified": "Sat, 31 Oct 2020 14:34:07 GMT",
    "age": "221578",
    "x-amz-request-id": "F284F2267B98D5CB",
    "cache-control": "public, max-age=31536000, immutable",
    "cf-cache-status": "HIT",
    "expect-ct": "max-age=604800, report-uri=\"https://report-uri.cloudflare.com/cdn-cgi/beacon/expect-ct\"",
    "x-amz-id-2": "gwgoL5/cZZ/d9xAOCejgbQVejTjgZX65uog3ClYMExEZa9mJJCuIaMYdI6+mt5ELo+KP1oL6aYM=",
    "etag": "\"296cf27dd28a0eceaa1de08a12ca7e45\"",
    "access-control-allow-origin": "*",
    "cf-request-id": "06467002d800007415b48a9000000001",
    "x-amz-version-id": "6dcKEeYjKKE.i67SUFPjMsZiE1noHQS_",
    "vary": "Accept-Encoding",
    "server": "cloudflare",
    "date": "Sat, 07 Nov 2020 22:32:29 GMT",
    "content-length": "7212",
    "accept-ranges": "bytes",
    "report-to": "{\"endpoints\":[{\"url\":\"https:\\/\\/a.nel.cloudflare.com\\/report?s=Tm%2FefdYwm0afSzarLWLa9F6zC68lfeAoG5%2BxO6cvv4G5d%2BZcHnHkLxJ3RhK%2FJPEX2C9odX0ln4XEcSmVLjy0BLw%2FUSHGSslmD14%3D\"}],\"group\":\"cf-nel\",\"max_age\":604800}",
    "content-type": "application/typescript; charset=utf-8"
  },
  "url": "https://deno.land/std@0.76.0/fmt/colors.ts"
}